README.md
__init__.py
kqlpythondir.py
realtimekql.py
setup.cfg
lib/Azure.Core.dll
lib/Azure.Storage.Blobs.dll
lib/Azure.Storage.Common.dll
lib/Kusto.Cloud.Platform.Azure.dll
lib/Kusto.Cloud.Platform.dll
lib/Kusto.Data.dll
lib/Kusto.Ingest.dll
lib/Kusto.Language.dll
lib/Microsoft.Azure.KeyVault.Core.dll
lib/Microsoft.Azure.KeyVault.WebKey.dll
lib/Microsoft.Azure.KeyVault.dll
lib/Microsoft.Bcl.AsyncInterfaces.dll
lib/Microsoft.IO.RecyclableMemoryStream.dll
lib/Microsoft.IdentityModel.Clients.ActiveDirectory.dll
lib/Microsoft.Rest.ClientRuntime.Azure.dll
lib/Microsoft.Rest.ClientRuntime.dll
lib/Microsoft.Rx.Kql.dll
lib/Microsoft.Syslog.dll
lib/Microsoft.Syslog.pdb
lib/Microsoft.WindowsAzure.Storage.dll
lib/Newtonsoft.Json.dll
lib/RealTimeKqlLibrary.dll
lib/RealTimeKqlLibrary.pdb
lib/System.Buffers.dll
lib/System.CodeDom.dll
lib/System.Collections.Immutable.dll
lib/System.Data.HashFunction.Core.dll
lib/System.Data.HashFunction.Interfaces.dll
lib/System.Data.HashFunction.xxHash.dll
lib/System.Diagnostics.DiagnosticSource.dll
lib/System.Memory.dll
lib/System.Numerics.Vectors.dll
lib/System.Reactive.Linq.dll
lib/System.Reactive.dll
lib/System.Runtime.CompilerServices.Unsafe.dll
lib/System.Security.Cryptography.ProtectedData.dll
lib/System.Security.Principal.Windows.dll
lib/System.Text.Encodings.Web.dll
lib/System.Text.Json.dll
lib/System.Threading.Tasks.Extensions.dll
lib/System.ValueTuple.dll
lib/Tx.Core.dll
lib/Tx.Windows.Logs.dll
lib/Tx.Windows.dll
realtimekql-2.2.4.data/data/lib/Azure.Core.dll
realtimekql-2.2.4.data/data/lib/Azure.Storage.Blobs.dll
realtimekql-2.2.4.data/data/lib/Azure.Storage.Common.dll
realtimekql-2.2.4.data/data/lib/Kusto.Cloud.Platform.Azure.dll
realtimekql-2.2.4.data/data/lib/Kusto.Cloud.Platform.dll
realtimekql-2.2.4.data/data/lib/Kusto.Data.dll
realtimekql-2.2.4.data/data/lib/Kusto.Ingest.dll
realtimekql-2.2.4.data/data/lib/Kusto.Language.dll
realtimekql-2.2.4.data/data/lib/Microsoft.Azure.KeyVault.Core.dll
realtimekql.egg-info/PKG-INFO
realtimekql.egg-info/SOURCES.txt
realtimekql.egg-info/dependency_links.txt
realtimekql.egg-info/requires.txt
realtimekql.egg-info/top_level.txt
realtimekql-2.2.4.dist-info/METADATA
realtimekql-2.2.4.dist-info/WHEEL
realtimekql-2.2.4.dist-info/top_level.txt
realtimekql-2.2.4.dist-info/RECORD
