Metadata-Version: 2.1
Name: realtimekql
Version: 2.2.4
Summary: A module for exploring real-time streams of events
Home-page: https://github.com/microsoft/kqltools
Author: CDOC Engineering Open Source
Author-email: CDOCEngOpenSourceAdm@microsoft.com
License: UNKNOWN
Platform: UNKNOWN
Classifier: Environment :: Console
Classifier: Intended Audience :: End Users/Desktop
Classifier: Intended Audience :: Developers
Classifier: License :: OSI Approved :: Apache Software License
Classifier: Natural Language :: English
Classifier: Operating System :: Microsoft :: Windows
Classifier: Programming Language :: C#
Classifier: Programming Language :: Python :: 3
Classifier: Topic :: Security
Classifier: Topic :: System :: Logging
Classifier: Topic :: System :: Monitoring
Classifier: Topic :: System :: Networking
Classifier: Topic :: System :: Networking :: Monitoring
Classifier: Topic :: System :: Operating System
Classifier: Topic :: System :: Operating System Kernels
Requires-Dist: pythonnet
Requires-Dist: pandas
Requires-Dist: azure.kusto.data
Requires-Dist: azure.kusto.ingest
